[
 {
    "first_name": "KEAN",
    "last_name": "ABORDO",
    "middle_name": "SULLIVAN",
    "lrn": "104973180027",
    "gender": "M",
    "birthdate": "2012-11-15",
    "section_id":  7,
    "home_address": " 301 Cacarong Matanda, Pandi, Bulacan",
    "guardian_name": "SULLIVAN,JANET",
    "contact_number": "09158741126",
    "remarks": ""
  },
  {
    "first_name": "ROBERT, JR ",
    "last_name": "BERINA",
    "middle_name": "DUMAPIAS",
    "lrn": "104973180032",
    "gender": "M",
    "birthdate": "2012-09-21",
    "section_id":  7,
    "home_address": " 421 Cacarong Matanda, Pandi, Bulacan",
    "guardian_name": "DUMAPIAS,MARICEL",
    "contact_number": "09175842367",
    "remarks": ""
  },
   {
    "first_name": "ZYMON JOSEPH",
    "last_name": "BULANADI",
    "middle_name": "SOSA",
    "lrn": "104973180029",
    "gender": "M",
    "birthdate": "2013-10-31",
    "section_id":  7,
    "home_address": "028 Cacarong Matanda, Pandi, Bulacan",
    "guardian_name": "BULANADI, JOSEPH ",
    "contact_number": "09152478963",
    "remarks": ""
  },
   {
    "first_name": "MANNY",
    "last_name": "CANO",
    "middle_name": "LADERAS",
    "lrn": "104973180071",
    "gender": "M",
    "birthdate": "2012-10-03",
    "section_id":  7,
    "home_address": "123 Cacarong Matanda, Pandi, Bulacan",
    "guardian_name": "LADERAS,MELINDA",
    "contact_number": "09275841036",
    "remarks": ""
  },
   {
    "first_name": "JOHN ANTHONY",
    "last_name": "CATAMORA",
    "middle_name": "DIAZ",
    "lrn": "104973170138",
    "gender": "M",
    "birthdate": "2013-01-02",
    "section_id":  7,
    "home_address": " 874 Cacarong Matanda, Pandi, Bulacan",
    "guardian_name": "CATAMORA, ATHONY",
    "contact_number": "09102457896",
    "remarks": ""
  },
   {
    "first_name": "JUSTINE KOBE",
    "last_name": "CRUZ",
    "middle_name": "TEJADA",
    "lrn": "104973180020",
    "gender": "M",
    "birthdate": "2013-06-13",
    "section_id":  7,
    "home_address": "046 Cacarong Matanda, Pandi, Bulacan",
    "guardian_name": "TEJADA,JOCHELLE",
    "contact_number": "09264478951",
    "remarks": ""
  },
   {
    "first_name": "ANTHON,",
    "last_name": "CUDAL",
    "middle_name": "DUMAPIAS",
    "lrn": "104973180034",
    "gender": "M",
    "birthdate": "2013-06-13",
    "section_id":  7,
    "home_address": "853 Cacarong Matanda, Pandi, Bulacan",
    "guardian_name": "CUDAL, DANILO ",
    "contact_number": "09358741203",
    "remarks": ""
  },
   {
    "first_name": "RENALD",
    "last_name": "DE GUZMAN",
    "middle_name": "LADERAS",
    "lrn": "104973180031",
    "gender": "M",
    "birthdate": "2012-12-03",
    "section_id":  7,
    "home_address": "362 Cacarong Matanda, Pandi, Bulacan",
    "guardian_name": "DE GUZMAN, RONALDO ",
    "contact_number": "09182458790",
    "remarks": ""
  },
   {
    "first_name": "ARCHIE",
    "last_name": "DE LUNA",
    "middle_name": "MORENO",
    "lrn": "104973180028",
    "gender": "M",
    "birthdate": "2011-08-08",
    "section_id":  7,
    "home_address": "426 Cacarong Matanda, Pandi, Bulacan",
    "guardian_name": "MORENO,ALMA",
    "contact_number": "09102547891",
    "remarks": ""
  },
   {
    "first_name": "JOHN JASPER",
    "last_name": "DEL ROSARIO",
    "middle_name": "DELOS SANTOS",
    "lrn": "104973180270",
    "gender": "M",
    "birthdate": "2013-02-18",
    "section_id":  7,
    "home_address": "624 Cacarong Matanda, Pandi, Bulacan",
    "guardian_name": "DEL ROSARIO, JONEL ",
    "contact_number": "09165478296",
    "remarks": ""
  },
   {
    "first_name": "JOSHUA RAIN",
    "last_name": "DELA CRUZ",
    "middle_name": "LACSON",
    "lrn": "104973180019",
    "gender": "M",
    "birthdate": "2012-09-11",
    "section_id":  7,
    "home_address": "587 Cacarong Matanda, Pandi, Bulacan",
    "guardian_name": "LACSON,REGINA",
    "contact_number": "09154782636",
    "remarks": ""
  },
   {
    "first_name": "STEVEN",
    "last_name": "DELA TORRE",
    "middle_name": "FRANCISCO",
    "lrn": "104973180026",
    "gender": "M",
    "birthdate": "2012-09-11",
    "section_id":  7,
    "home_address": " Cacarong Matanda, Pandi, Bulacan",
    "guardian_name": "FRANCISCO,GINA",
    "contact_number": "09182647582",
    "remarks": ""
  },
   {
    "first_name": "KHING ACE",
    "last_name": "DELOS SANTOS",
    "middle_name": "DUGOS",
    "lrn": "104973180018",
    "gender": "M",
    "birthdate": "2013-04-09",
    "section_id":  7,
    "home_address": "624 Cacarong Matanda, Pandi, Bulacan",
    "guardian_name": "DUGOS,CONELYN",
    "contact_number": "09176845297",
    "remarks": ""
  },
   {
    "first_name": "JES",
    "last_name": "ESTEBAN",
    "middle_name": "RESARE",
    "lrn": "104973180017",
    "gender": "M",
    "birthdate": "2012-07-08",
    "section_id":  7,
    "home_address": " 248 Cacarong Matanda, Pandi, Bulacan",
    "guardian_name": "RESARE,KIMBERLY",
    "contact_number": "09754123687",
    "remarks": ""
  },
   {
    "first_name": "ROBERTO",
    "last_name": "FRANCISCO",
    "middle_name": "GREJALVO",
    "lrn": "104973180176",
    "gender": "M",
    "birthdate": "2013-01-02",
    "section_id":  7,
    "home_address": "459 Cacarong Matanda, Pandi, Bulacan",
    "guardian_name": "GREJALVO,FRANCIS",
    "contact_number": "09189652314",
    "remarks": ""
  },

  // femalessss

   {
    "first_name": "NIKKA",
    "last_name": "ABKILAN",
    "middle_name": "DONAIRE",
    "lrn": "104973180010",
    "gender": "F",
    "birthdate": "2013-01-0223",
    "section_id":  7,
    "home_address": " 763 Cacarong Matanda, Pandi, Bulacan",
    "guardian_name": "DONAIRE,MARISSA",
    "contact_number": "09178954213",
    "remarks": ""
  },
   
    {
    "first_name": "SHAINNA",
    "last_name": "ALVARADO",
    "middle_name": "SANTILLESIS",
    "lrn": "104973180014",
    "gender": "F",
    "birthdate": "2013-03-14",
    "section_id":  7,
    "home_address": " 357 Cacarong Matanda, Pandi, Bulacan",
    "guardian_name": "ALVARADO, SIXTO",
    "contact_number": "09256487952",
    "remarks": ""
  },
    {
    "first_name": "RHIAN",
    "last_name": "BALITON",
    "middle_name": "BALOLOY",
    "lrn": "104973180070",
    "gender": "F",
    "birthdate": "2013-03-06",
    "section_id":  7,
    "home_address": " 952 Cacarong Matanda, Pandi, Bulacan",
    "guardian_name": "BALOLOY,CRISTINA",
    "contact_number": "09265489541",
    "remarks": ""
  },
    {
    "first_name": "HANNAH CLAIRE",
    "last_name": "BALUYOT",
    "middle_name": "REFUGIO",
    "lrn": "104973180004",
    "gender": "F",
    "birthdate": "2013-06-13",
    "section_id":  7,
    "home_address": " 101 Cacarong Matanda, Pandi, Bulacan",
    "guardian_name": "BALUYOT, JOSEPH",
    "contact_number": "09156321547",
    "remarks": ""
  },
    {
    "first_name": "PRINCESS ALTHEA",
    "last_name": "BANGALISAN",
    "middle_name": "",
    "lrn": "104973180269",
    "gender": "F",
    "birthdate": "2013-09-01",
    "section_id":  7,
    "home_address": "010 Cacarong Matanda, Pandi, Bulacan",
    "guardian_name": "BANGALISAN,CADIDIA",
    "contact_number": "09236589741",
    "remarks": ""
  },
    {
    "first_name": "MARION ROXANNE",
    "last_name": "BARCELO",
    "middle_name": "TIANGSON",
    "lrn": "136450170096",
    "gender": "F",
    "birthdate": "2011-12-24",
    "section_id":  7,
    "home_address": "020 Cacarong Matanda, Pandi, Bulacan",
    "guardian_name": "TIANGSON,ROWENA",
    "contact_number": "09203654189",
    "remarks": ""
  },
    {
    "first_name": "BERDESO",
    "last_name": "CAPUZ",
    "middle_name": "DANAYA",
    "lrn": "104973180268",
    "gender": "F",
    "birthdate": "2012-01-06",
    "section_id":  7,
    "home_address": " 111 Cacarong Matanda, Pandi, Bulacan",
    "guardian_name": "CAPUZ, DANILO",
    "contact_number": "09558741230",
    "remarks": ""
  },
    {
    "first_name": "ARTH JANINE",
    "last_name": "BIAGO",
    "middle_name": "BECHAYDA",
    "lrn": "104973180074",
    "gender": "F",
    "birthdate": "2013-07-19",
    "section_id":  7,
    "home_address": " 951 Cacarong Matanda, Pandi, Bulacan",
    "guardian_name": "BIAGO, RODRIGO",
    "contact_number": "09978541261",
    "remarks": ""
  },
    {
    "first_name": "MARY ANN",
    "last_name": "CELESTINO",
    "middle_name": "TOLOSA",
    "lrn": "104973170124",
    "gender": "F",
    "birthdate": "2013-10-19",
    "section_id":  7,
    "home_address": " 222 Cacarong Matanda, Pandi, Bulacan",
    "guardian_name": "CELESTINO, ANGELITO",
    "contact_number": "09106241305",
    "remarks": ""
  },
    {
    "first_name": "CELINA CLAUDINE",
    "last_name": "CONDENO,",
    "middle_name": "JACA",
    "lrn": "104973180011",
    "gender": "F",
    "birthdate": "2013-04-111",
    "section_id":  7,
    "home_address": " 323 Cacarong Matanda, Pandi, Bulacan",
    "guardian_name": "CONDENO, GONZALO ",
    "contact_number": "09274851261",
    "remarks": ""
  },
   
   
]